pubsub_utils/__init__.py
pubsub_utils/errors.py
pubsub_utils/publisher/__init__.py
pubsub_utils/publisher/base.py
pubsub_utils/subscriber/__init__.py
pubsub_utils/subscriber/base.py
pubsub_utils/topic/__init__.py
pubsub_utils/topic/base.py
pubsub_utils-1.0.0.dist-info/LICENSE
pubsub_utils-1.0.0.dist-info/METADATA
pubsub_utils-1.0.0.dist-info/WHEEL
pubsub_utils-1.0.0.dist-info/top_level.txt
pubsub_utils-1.0.0.dist-info/RECORD
