Metadata-Version: 2.1
Name: pubsub-utils
Version: 1.0.0
Summary: Pub sub package 
Home-page: https://bitbucket.org/wonderfulagency/pubsub-utils
Author: Wonderful Agency
Author-email: web.devops@wonderful.com
License: UNKNOWN
Platform: UNKNOWN
Classifier: Programming Language :: Python :: 3.9
Classifier: Programming Language :: Python :: 3.10
Classifier: License :: OSI Approved :: MIT License
Classifier: Operating System :: OS Independent
Requires-Python: >=3.9
License-File: LICENSE
Requires-Dist: google-cloud-pubsub (>=2.0.0)
